<entry>
  <header>
    <lexical_unit id="15596">črnogled</lexical_unit>
    <category>pridevnik</category>
    <measure type="frequency" source="Gigafida 1.0">3357</measure>
  </header>
  <body>
    <sense>
      <gramrels>
        <gramrel name="PBZ0 glede sbz2">
          <collocations>
            <collocation form="črnogled glede prihodnosti" cluster="1" frequency="14" logDice="10.85">
              <comp position="1" type="headword" sloleks="LE_de7d7b38e872496c91b9bac2a6c688e1">črnogled</comp>
              <comp position="2" type="other" sloleks="LE_e27cbf8b338f86710828a4c5c2fee21f">glede</comp>
              <comp position="3" type="collocate" sloleks="LE_0f987c9335ef2920c7afd61c36a192ed">prihodnosti</comp>
            </collocation>
            <collocation form="črnogled glede razvoja" cluster="2" frequency="5" logDice="10.66">
              <comp position="1" type="headword" sloleks="LE_de7d7b38e872496c91b9bac2a6c688e1">črnogled</comp>
              <comp position="2" type="other" sloleks="LE_e27cbf8b338f86710828a4c5c2fee21f">glede</comp>
              <comp position="3" type="collocate" sloleks="LE_59210d6d596fdb364ef1653bd49f3a75">razvoja</comp>
            </collocation>
            <collocation form="črnogled glede možnosti" cluster="3" frequency="7" logDice="10.38">
              <comp position="1" type="headword" sloleks="LE_de7d7b38e872496c91b9bac2a6c688e1">črnogled</comp>
              <comp position="2" type="other" sloleks="LE_e27cbf8b338f86710828a4c5c2fee21f">glede</comp>
              <comp position="3" type="collocate" sloleks="LE_2e00efc106e45a8fd5ad17e06d9e6382">možnosti</comp>
            </collocation>
          </collocations>
        </gramrel>
        <gramrel name="PBZ0 in/ali pbz0">
          <collocations>
            <collocation form="črnogled in depresiven" cluster="1" frequency="5" logDice="7.43">
              <comp position="1" type="headword" sloleks="LE_de7d7b38e872496c91b9bac2a6c688e1">črnogled</comp>
              <comp position="2" type="other" sloleks="LE_0e08f5e226294035b0271fc4207cc81b">in/ali</comp>
              <comp position="3" type="collocate" sloleks="LE_ac04ad54bf1c8f0d95b4eb7ea46046b4">depresiven</comp>
            </collocation>
          </collocations>
        </gramrel>
        <gramrel name="PBZ0 sbz0">
          <collocations>
            <collocation form="črnogleda napoved" cluster="1" frequency="715" logDice="8.79">
              <comp position="1" type="headword" sloleks="LE_de7d7b38e872496c91b9bac2a6c688e1">črnogleda</comp>
              <comp position="2" type="collocate" sloleks="LE_857d50f24958cb465551230f8a46f709">napoved</comp>
            </collocation>
            <collocation form="črnogleda ocena" cluster="1" frequency="33" logDice="3.73">
              <comp position="1" type="headword" sloleks="LE_de7d7b38e872496c91b9bac2a6c688e1">črnogleda</comp>
              <comp position="2" type="collocate" sloleks="LE_876e5c609b3c91704b14383926ee218d">ocena</comp>
            </collocation>
            <collocation form="črnogled pesimist" cluster="2" frequency="8" logDice="6.84">
              <comp position="1" type="headword" sloleks="LE_de7d7b38e872496c91b9bac2a6c688e1">črnogled</comp>
              <comp position="2" type="collocate" sloleks="LE_400f119eadb0ed7e5f1f06f513a84eea">pesimist</comp>
            </collocation>
            <collocation form="črnogledo pričakovanje" cluster="3" frequency="23" logDice="4.93">
              <comp position="1" type="headword" sloleks="LE_de7d7b38e872496c91b9bac2a6c688e1">črnogledo</comp>
              <comp position="2" type="collocate" sloleks="LE_f1642d2e0ee399df024a8a8c36785883">pričakovanje</comp>
            </collocation>
            <collocation form="črnogledo razpoloženje" cluster="3" frequency="17" logDice="4.66">
              <comp position="1" type="headword" sloleks="LE_de7d7b38e872496c91b9bac2a6c688e1">črnogledo</comp>
              <comp position="2" type="collocate" sloleks="LE_8a67a03ef31d21945ab05558e67e2cde">razpoloženje</comp>
            </collocation>
            <collocation form="črnogledo razmišljanje" cluster="4" frequency="9" logDice="3.74">
              <comp position="1" type="headword" sloleks="LE_de7d7b38e872496c91b9bac2a6c688e1">črnogledo</comp>
              <comp position="2" type="collocate" sloleks="LE_c1397f9b6b6c049143a63321f5b45348">razmišljanje</comp>
            </collocation>
            <collocation form="črnogleda prihodnost" cluster="5" frequency="11" logDice="3.06">
              <comp position="1" type="headword" sloleks="LE_de7d7b38e872496c91b9bac2a6c688e1">črnogleda</comp>
              <comp position="2" type="collocate" sloleks="LE_0f987c9335ef2920c7afd61c36a192ed">prihodnost</comp>
            </collocation>
            <collocation form="črnogled pogled" cluster="6" frequency="14" logDice="2.41">
              <comp position="1" type="headword" sloleks="LE_de7d7b38e872496c91b9bac2a6c688e1">črnogled</comp>
              <comp position="2" type="collocate" sloleks="LE_456820bc1f399479d902f190585f0938">pogled</comp>
            </collocation>
            <collocation form="črnogledo poročilo" cluster="7" frequency="13" logDice="2.25">
              <comp position="1" type="headword" sloleks="LE_de7d7b38e872496c91b9bac2a6c688e1">črnogledo</comp>
              <comp position="2" type="collocate" sloleks="LE_00452c6ec77fc0b47997a85c80913ca4">poročilo</comp>
            </collocation>
            <collocation form="črnogledo mnenje" cluster="7" frequency="9" logDice="1.43">
              <comp position="1" type="headword" sloleks="LE_de7d7b38e872496c91b9bac2a6c688e1">črnogledo</comp>
              <comp position="2" type="collocate" sloleks="LE_570e657c7ba1bf69e788fb96b4ad3409">mnenje</comp>
            </collocation>
            <collocation form="črnogled človek" cluster="8" frequency="19" logDice="0.96">
              <comp position="1" type="headword" sloleks="LE_de7d7b38e872496c91b9bac2a6c688e1">črnogled</comp>
              <comp position="2" type="collocate" sloleks="LE_53ae3a1a0ac28b4bef77406c6bf914a8">človek</comp>
            </collocation>
            <collocation form="črnogledo predvidevanje" cluster="9" frequency="10" logDice="6.63">
              <comp position="1" type="headword" sloleks="LE_de7d7b38e872496c91b9bac2a6c688e1">črnogledo</comp>
              <comp position="2" type="collocate" sloleks="LE_dd64a9814e8aabd56343d116beeada8e">predvidevanje</comp>
            </collocation>
            <collocation form="črnogled napovedovalec" cluster="10" frequency="10" logDice="6.47">
              <comp position="1" type="headword" sloleks="LE_de7d7b38e872496c91b9bac2a6c688e1">črnogled</comp>
              <comp position="2" type="collocate" sloleks="LE_7f3c45acd3c27633585dbb900d83b2a3">napovedovalec</comp>
            </collocation>
            <collocation form="črnogled prerok" cluster="11" frequency="8" logDice="6.2">
              <comp position="1" type="headword" sloleks="LE_de7d7b38e872496c91b9bac2a6c688e1">črnogled</comp>
              <comp position="2" type="collocate" sloleks="LE_9d61a73686d2d3c3e47f933c70231bac">prerok</comp>
            </collocation>
            <collocation form="črnogled scenarij" cluster="12" frequency="55" logDice="6.05">
              <comp position="1" type="headword" sloleks="LE_de7d7b38e872496c91b9bac2a6c688e1">črnogled</comp>
              <comp position="2" type="collocate" sloleks="LE_7e8abe4fde9d78d012917b967f541319">scenarij</comp>
            </collocation>
            <collocation form="črnogled analitik" cluster="13" frequency="22" logDice="5.79">
              <comp position="1" type="headword" sloleks="LE_de7d7b38e872496c91b9bac2a6c688e1">črnogled</comp>
              <comp position="2" type="collocate" sloleks="LE_9c58b357b8ef042c7f5b19405e0c2252">analitik</comp>
            </collocation>
            <collocation form="črnogled poznavalec" cluster="13" frequency="14" logDice="4.89">
              <comp position="1" type="headword" sloleks="LE_de7d7b38e872496c91b9bac2a6c688e1">črnogled</comp>
              <comp position="2" type="collocate" sloleks="LE_c179cfda268388f9786b426e0f14a904">poznavalec</comp>
            </collocation>
            <collocation form="črnogleda misel" cluster="14" frequency="44" logDice="4.96">
              <comp position="1" type="headword" sloleks="LE_de7d7b38e872496c91b9bac2a6c688e1">črnogleda</comp>
              <comp position="2" type="collocate" sloleks="LE_5c7f7f0d0d08b8f576a9107f674e22dd">misel</comp>
            </collocation>
          </collocations>
        </gramrel>
        <gramrel name="gbz PBZ1">
          <collocations>
            <collocation form="napovedovati črnogled" cluster="1" frequency="9" logDice="9.48">
              <comp position="1" type="collocate" sloleks="LE_35cd3aa7a011ac9009e187675686fad6">napovedovati</comp>
              <comp position="2" type="headword" sloleks="LE_de7d7b38e872496c91b9bac2a6c688e1">črnogled</comp>
            </collocation>
            <collocation form="postati črnogled" cluster="2" frequency="11" logDice="2.26">
              <comp position="1" type="collocate" sloleks="LE_c8e9d4f0bbc764e535f72bddd3507947|LE_c2ff60a03966bdff6d1c8481489399e9">postati</comp>
              <comp position="2" type="headword" sloleks="LE_de7d7b38e872496c91b9bac2a6c688e1">črnogled</comp>
            </collocation>
          </collocations>
        </gramrel>
        <gramrel name="rbz PBZ0">
          <collocations>
            <collocation form="najbolj črnogled" cluster="1" frequency="420" logDice="4.44">
              <comp position="1" type="collocate" sloleks="LE_72b2a3522865b723e8c26b8ade696fca">najbolj</comp>
              <comp position="2" type="headword" sloleks="LE_de7d7b38e872496c91b9bac2a6c688e1">črnogled</comp>
            </collocation>
            <collocation form="bolj črnogled" cluster="1" frequency="320" logDice="4.02">
              <comp position="1" type="collocate" sloleks="LE_eb5c9ce617296e17362f1f97122c4c36">bolj</comp>
              <comp position="2" type="headword" sloleks="LE_de7d7b38e872496c91b9bac2a6c688e1">črnogled</comp>
            </collocation>
            <collocation form="preveč črnogled" cluster="1" frequency="155" logDice="5.54">
              <comp position="1" type="collocate" sloleks="LE_1a80970ab70c9c14f7164bfde4d5796e">preveč</comp>
              <comp position="2" type="headword" sloleks="LE_de7d7b38e872496c91b9bac2a6c688e1">črnogled</comp>
            </collocation>
            <collocation form="zelo črnogled" cluster="1" frequency="102" logDice="1.9">
              <comp position="1" type="collocate" sloleks="LE_195d60c164b7057008d21b29153e2352">zelo</comp>
              <comp position="2" type="headword" sloleks="LE_de7d7b38e872496c91b9bac2a6c688e1">črnogled</comp>
            </collocation>
            <collocation form="precej črnogled" cluster="1" frequency="68" logDice="3.41">
              <comp position="1" type="collocate" sloleks="LE_e0671a56c827200d0ebc033694e6214b">precej</comp>
              <comp position="2" type="headword" sloleks="LE_de7d7b38e872496c91b9bac2a6c688e1">črnogled</comp>
            </collocation>
            <collocation form="manj črnogled" cluster="1" frequency="44" logDice="2.82">
              <comp position="1" type="collocate" sloleks="LE_ecab8216e0225b7e80d79b53bd9b8959">manj</comp>
              <comp position="2" type="headword" sloleks="LE_de7d7b38e872496c91b9bac2a6c688e1">črnogled</comp>
            </collocation>
            <collocation form="nekoliko črnogled" cluster="1" frequency="27" logDice="2.89">
              <comp position="1" type="collocate" sloleks="LE_63286f71b723669983b38884d53a9abc">nekoliko</comp>
              <comp position="2" type="headword" sloleks="LE_de7d7b38e872496c91b9bac2a6c688e1">črnogled</comp>
            </collocation>
            <collocation form="malce črnogled" cluster="1" frequency="11" logDice="3.26">
              <comp position="1" type="collocate" sloleks="LE_2eec11a38ac5bbb5fa6d7682c1224a82">malce</comp>
              <comp position="2" type="headword" sloleks="LE_de7d7b38e872496c91b9bac2a6c688e1">črnogled</comp>
            </collocation>
            <collocation form="malo črnogled" cluster="1" frequency="10" logDice="1.93">
              <comp position="1" type="collocate" sloleks="LE_d41681585195c3924afdc162614c2939">malo</comp>
              <comp position="2" type="headword" sloleks="LE_de7d7b38e872496c91b9bac2a6c688e1">črnogled</comp>
            </collocation>
            <collocation form="popolnoma črnogled" cluster="1" frequency="7" logDice="1.08">
              <comp position="1" type="collocate" sloleks="LE_cf3152eef1d42e2e987683663209bafc">popolnoma</comp>
              <comp position="2" type="headword" sloleks="LE_de7d7b38e872496c91b9bac2a6c688e1">črnogled</comp>
            </collocation>
            <collocation form="toliko črnogled" cluster="1" frequency="5" logDice="1.4">
              <comp position="1" type="collocate" sloleks="LE_e8a73a0e682431303071ff7537eabf4b">toliko</comp>
              <comp position="2" type="headword" sloleks="LE_de7d7b38e872496c91b9bac2a6c688e1">črnogled</comp>
            </collocation>
            <collocation form="dokaj črnogled" cluster="2" frequency="25" logDice="3.56">
              <comp position="1" type="collocate" sloleks="LE_90c3e789d159a5b43e1f600807dba440">dokaj</comp>
              <comp position="2" type="headword" sloleks="LE_de7d7b38e872496c91b9bac2a6c688e1">črnogled</comp>
            </collocation>
            <collocation form="pretirano črnogled" cluster="2" frequency="18" logDice="5.31">
              <comp position="1" type="collocate" sloleks="LE_8de0ab7a7ed22d3cca1b5eb9a04db1af">pretirano</comp>
              <comp position="2" type="headword" sloleks="LE_de7d7b38e872496c91b9bac2a6c688e1">črnogled</comp>
            </collocation>
            <collocation form="hudo črnogled" cluster="2" frequency="8" logDice="2.97">
              <comp position="1" type="collocate" sloleks="LE_feb425a4578d9be162c4327513777270">hudo</comp>
              <comp position="2" type="headword" sloleks="LE_de7d7b38e872496c91b9bac2a6c688e1">črnogled</comp>
            </collocation>
            <collocation form="silno črnogled" cluster="2" frequency="7" logDice="4.47">
              <comp position="1" type="collocate" sloleks="LE_ca41b9cc2e2357ce392c6861d396e183">silno</comp>
              <comp position="2" type="headword" sloleks="LE_de7d7b38e872496c91b9bac2a6c688e1">črnogled</comp>
            </collocation>
            <collocation form="skrajno črnogled" cluster="2" frequency="7" logDice="3.49">
              <comp position="1" type="collocate" sloleks="LE_50bd085be9fea6c2fd7222a14ab31702">skrajno</comp>
              <comp position="2" type="headword" sloleks="LE_de7d7b38e872496c91b9bac2a6c688e1">črnogled</comp>
            </collocation>
            <collocation form="izredno črnogled" cluster="2" frequency="5" logDice="0.88">
              <comp position="1" type="collocate" sloleks="LE_b0c342862689aaa5fb70350f5e76768e">izredno</comp>
              <comp position="2" type="headword" sloleks="LE_de7d7b38e872496c91b9bac2a6c688e1">črnogled</comp>
            </collocation>
            <collocation form="tako črnogled" cluster="3" frequency="207" logDice="3.12">
              <comp position="1" type="collocate" sloleks="LE_a43856b7d4097e8e3ab29718abb1acb7">tako</comp>
              <comp position="2" type="headword" sloleks="LE_de7d7b38e872496c91b9bac2a6c688e1">črnogled</comp>
            </collocation>
            <collocation form="vedno črnogled" cluster="3" frequency="12" logDice="0.97">
              <comp position="1" type="collocate" sloleks="LE_eaabd5718a27f818fd47358031426355">vedno</comp>
              <comp position="2" type="headword" sloleks="LE_de7d7b38e872496c91b9bac2a6c688e1">črnogled</comp>
            </collocation>
            <collocation form="prej črnogled" cluster="3" frequency="6" logDice="2.15">
              <comp position="1" type="collocate" sloleks="LE_25430d3959f90161be5f8125f60962ef">prej</comp>
              <comp position="2" type="headword" sloleks="LE_de7d7b38e872496c91b9bac2a6c688e1">črnogled</comp>
            </collocation>
            <collocation form="torej črnogled" cluster="3" frequency="5" logDice="1.48">
              <comp position="1" type="collocate" sloleks="LE_77b94d141697df1606f829a597a115e8">torej</comp>
              <comp position="2" type="headword" sloleks="LE_de7d7b38e872496c91b9bac2a6c688e1">črnogled</comp>
            </collocation>
          </collocations>
        </gramrel>
        <gramrel name="sbz1 vez-gbz PBZ1">
          <collocations>
            <collocation form="napoved je črnogleda" cluster="1" frequency="15" logDice="9.77">
              <comp position="1" type="collocate" sloleks="LE_857d50f24958cb465551230f8a46f709">napoved</comp>
              <comp position="2" type="other" sloleks="LE_4ce899cffc87547d3bbc80f27408a816">je</comp>
              <comp position="3" type="headword" sloleks="LE_de7d7b38e872496c91b9bac2a6c688e1">črnogleda</comp>
            </collocation>
          </collocations>
        </gramrel>
      </gramrels>
    </sense>
  </body>
</entry>
