<entry>
  <header>
    <lexical_unit id="77019">pastor</lexical_unit>
    <category>samostalnik</category>
    <measure type="frequency" source="Gigafida 1.0">2301</measure>
  </header>
  <body>
    <sense>
      <gramrels>
        <gramrel name="SBZ0 v sbz5">
          <collocations>
            <collocation form="pastor v soseski" cluster="1" frequency="5" logDice="6.42">
              <comp position="1" type="headword" sloleks="LE_c4d623bd43bf2e745724193fe576f1c5">pastor</comp>
              <comp position="2" type="other" sloleks="LE_6ee5842d0266489f7232f3339975492f">v</comp>
              <comp position="3" type="collocate" sloleks="LE_56a059debef7056c910150bfad570e7c">soseski</comp>
            </collocation>
            <collocation form="pastor v cerkvi" cluster="2" frequency="10" logDice="4.59">
              <comp position="1" type="headword" sloleks="LE_c4d623bd43bf2e745724193fe576f1c5">pastor</comp>
              <comp position="2" type="other" sloleks="LE_6ee5842d0266489f7232f3339975492f">v</comp>
              <comp position="3" type="collocate" sloleks="LE_71364d2c460f04c8b1dbbb72e4901dca">cerkvi</comp>
            </collocation>
          </collocations>
        </gramrel>
        <gramrel name="SBZ0 z sbz2">
          <collocations>
            <collocation form="pastor s Floride" cluster="1" frequency="5" logDice="8.23">
              <comp position="1" type="headword" sloleks="LE_c4d623bd43bf2e745724193fe576f1c5">pastor</comp>
              <comp position="2" type="other" sloleks="LE_04a0f57716a1e9799e4307c4f13585cf">s</comp>
              <comp position="3" type="collocate" sloleks="LE_e2d96715420ddd713f399c5371a067d6">Floride</comp>
            </collocation>
          </collocations>
        </gramrel>
        <gramrel name="pbz0 SBZ0">
          <collocations>
            <collocation form="floridski pastor" cluster="1" frequency="44" logDice="9.25">
              <comp position="1" type="collocate" sloleks="LE_83dd5a072b9f050b3fbf9752beeb791d">floridski</comp>
              <comp position="2" type="headword" sloleks="LE_c4d623bd43bf2e745724193fe576f1c5">pastor</comp>
            </collocation>
            <collocation form="gromovniški pastor" cluster="2" frequency="15" logDice="9.07">
              <comp position="1" type="collocate" sloleks="LE_8fdba15aef9bb7fc348c92026686a8c3">gromovniški</comp>
              <comp position="2" type="headword" sloleks="LE_c4d623bd43bf2e745724193fe576f1c5">pastor</comp>
            </collocation>
            <collocation form="razvpit pastor" cluster="3" frequency="9" logDice="4.09">
              <comp position="1" type="collocate" sloleks="LE_00227ff779b8cc7acc2266b5c27a84af">razvpit</comp>
              <comp position="2" type="headword" sloleks="LE_c4d623bd43bf2e745724193fe576f1c5">pastor</comp>
            </collocation>
            <collocation form="ameriški pastor" cluster="4" frequency="49" logDice="1.65">
              <comp position="1" type="collocate" sloleks="LE_c02b8fa5427c488774a5c66efd9beafc">ameriški</comp>
              <comp position="2" type="headword" sloleks="LE_c4d623bd43bf2e745724193fe576f1c5">pastor</comp>
            </collocation>
            <collocation form="tamkajšnji pastor" cluster="4" frequency="10" logDice="2.17">
              <comp position="1" type="collocate" sloleks="LE_ee917dbffe3a1d9e41eb070a0d8ab9da">tamkajšnji</comp>
              <comp position="2" type="headword" sloleks="LE_c4d623bd43bf2e745724193fe576f1c5">pastor</comp>
            </collocation>
            <collocation form="baptističen pastor" cluster="5" frequency="19" logDice="9.02">
              <comp position="1" type="collocate" sloleks="LE_c82333321f08a33b9df64bd171b4c45f">baptističen</comp>
              <comp position="2" type="headword" sloleks="LE_c4d623bd43bf2e745724193fe576f1c5">pastor</comp>
            </collocation>
            <collocation form="evangeličanski pastor" cluster="6" frequency="43" logDice="8.36">
              <comp position="1" type="collocate" sloleks="LE_3c629fa781cf68a94e00e6783511e6fd">evangeličanski</comp>
              <comp position="2" type="headword" sloleks="LE_c4d623bd43bf2e745724193fe576f1c5">pastor</comp>
            </collocation>
            <collocation form="luteranski pastor" cluster="6" frequency="24" logDice="8.99">
              <comp position="1" type="collocate" sloleks="LE_3250b6d66cf1ee2e17039e15af326502">luteranski</comp>
              <comp position="2" type="headword" sloleks="LE_c4d623bd43bf2e745724193fe576f1c5">pastor</comp>
            </collocation>
            <collocation form="anglikanski pastor" cluster="6" frequency="19" logDice="8.26">
              <comp position="1" type="collocate" sloleks="LE_36759b5d22490616c6f5dc4f4ddcc852">anglikanski</comp>
              <comp position="2" type="headword" sloleks="LE_c4d623bd43bf2e745724193fe576f1c5">pastor</comp>
            </collocation>
            <collocation form="protestantski pastor" cluster="7" frequency="115" logDice="8.98">
              <comp position="1" type="collocate" sloleks="LE_c9ea894de808c28dbb62fe1339d8718d">protestantski</comp>
              <comp position="2" type="headword" sloleks="LE_c4d623bd43bf2e745724193fe576f1c5">pastor</comp>
            </collocation>
            <collocation form="vzhodnonemški pastor" cluster="8" frequency="10" logDice="6.57">
              <comp position="1" type="collocate" sloleks="LE_782fb45307e843cfdcff89eabb3197ab">vzhodnonemški</comp>
              <comp position="2" type="headword" sloleks="LE_c4d623bd43bf2e745724193fe576f1c5">pastor</comp>
            </collocation>
            <collocation form="temnopolt pastor" cluster="9" frequency="12" logDice="5.01">
              <comp position="1" type="collocate" sloleks="LE_76d10b8fb8f23dd1d8d832759727c176">temnopolt</comp>
              <comp position="2" type="headword" sloleks="LE_c4d623bd43bf2e745724193fe576f1c5">pastor</comp>
            </collocation>
            <collocation form="krščanski pastor" cluster="10" frequency="29" logDice="4.41">
              <comp position="1" type="collocate" sloleks="LE_ab123b765dfb28dda246c2315a9dca62">krščanski</comp>
              <comp position="2" type="headword" sloleks="LE_c4d623bd43bf2e745724193fe576f1c5">pastor</comp>
            </collocation>
          </collocations>
        </gramrel>
        <gramrel name="sbz0 SBZ2">
          <collocations>
            <collocation form="unionist pastorja" cluster="1" frequency="5" logDice="8.89">
              <comp position="1" type="collocate" sloleks="LE_0a1fbf7bce56e692494bae2885ec9179">unionist</comp>
              <comp position="2" type="headword" sloleks="LE_c4d623bd43bf2e745724193fe576f1c5">pastorja</comp>
            </collocation>
            <collocation form="Carlos Pastorja" cluster="2" frequency="11" logDice="7.78">
              <comp position="1" type="collocate" sloleks="LE_ccabe48795ab4c10d0b3230dbc9e7072">Carlos</comp>
              <comp position="2" type="headword" sloleks="LE_c4d623bd43bf2e745724193fe576f1c5">Pastorja</comp>
            </collocation>
            <collocation form="vloga pastorja" cluster="3" frequency="7" logDice="0.87">
              <comp position="1" type="collocate" sloleks="LE_89aaa09f7c3d2be0b532b62934f8cead">vloga</comp>
              <comp position="2" type="headword" sloleks="LE_c4d623bd43bf2e745724193fe576f1c5">pastorja</comp>
            </collocation>
            <collocation form="sin pastorja" cluster="4" frequency="22" logDice="4.77">
              <comp position="1" type="collocate" sloleks="LE_79e0b2d02a57a50544ca32d11914a5a7">sin</comp>
              <comp position="2" type="headword" sloleks="LE_c4d623bd43bf2e745724193fe576f1c5">pastorja</comp>
            </collocation>
            <collocation form="hči pastorja" cluster="4" frequency="15" logDice="6.02">
              <comp position="1" type="collocate" sloleks="LE_548160594c54c41472ed7de0d4dde6b4">hči</comp>
              <comp position="2" type="headword" sloleks="LE_c4d623bd43bf2e745724193fe576f1c5">pastorja</comp>
            </collocation>
            <collocation form="namera pastorja" cluster="5" frequency="8" logDice="5.76">
              <comp position="1" type="collocate" sloleks="LE_b42f39c4cdc97e8e23b14b50c620a845">namera</comp>
              <comp position="2" type="headword" sloleks="LE_c4d623bd43bf2e745724193fe576f1c5">pastorja</comp>
            </collocation>
            <collocation form="družina pastorja" cluster="6" frequency="11" logDice="3.84">
              <comp position="1" type="collocate" sloleks="LE_9a7d912c8ec5a6cbc42d2975b5563b34">družina</comp>
              <comp position="2" type="headword" sloleks="LE_c4d623bd43bf2e745724193fe576f1c5">pastorja</comp>
            </collocation>
            <collocation form="cerkev pastorja" cluster="6" frequency="9" logDice="3.19">
              <comp position="1" type="collocate" sloleks="LE_71364d2c460f04c8b1dbbb72e4901dca">cerkev</comp>
              <comp position="2" type="headword" sloleks="LE_c4d623bd43bf2e745724193fe576f1c5">pastorja</comp>
            </collocation>
            <collocation form="stranka pastorja" cluster="6" frequency="8" logDice="2.54">
              <comp position="1" type="collocate" sloleks="LE_945a204a300f28702820c4bc0481d2e7">stranka</comp>
              <comp position="2" type="headword" sloleks="LE_c4d623bd43bf2e745724193fe576f1c5">pastorja</comp>
            </collocation>
            <collocation form="služba pastorja" cluster="6" frequency="5" logDice="2.03">
              <comp position="1" type="collocate" sloleks="LE_595a77ebd11b27d069e3829b663f2954">služba</comp>
              <comp position="2" type="headword" sloleks="LE_c4d623bd43bf2e745724193fe576f1c5">pastorja</comp>
            </collocation>
            <collocation form="izjava pastorja" cluster="7" frequency="16" logDice="3.78">
              <comp position="1" type="collocate" sloleks="LE_43a60c321a9a7889eb71aacc9ccb368f">izjava</comp>
              <comp position="2" type="headword" sloleks="LE_c4d623bd43bf2e745724193fe576f1c5">pastorja</comp>
            </collocation>
            <collocation form="pastor Jeremiah" cluster="8" frequency="12" logDice="10.43">
              <comp position="1" type="headword" sloleks="LE_c4d623bd43bf2e745724193fe576f1c5">pastor</comp>
              <comp position="2" type="collocate" sloleks="">Jeremiah</comp>
            </collocation>
            <collocation form="pastor Terry" cluster="9" frequency="20" logDice="9.62">
              <comp position="1" type="headword" sloleks="LE_c4d623bd43bf2e745724193fe576f1c5">pastor</comp>
              <comp position="2" type="collocate" sloleks="LE_46aec1ad0e4295f95c908487626eaefa">Terry</comp>
            </collocation>
            <collocation form="pastor Iana" cluster="10" frequency="16" logDice="9.09">
              <comp position="1" type="headword" sloleks="LE_c4d623bd43bf2e745724193fe576f1c5">pastor</comp>
              <comp position="2" type="collocate" sloleks="LE_1fdc44f479f238cca9617ea18e29d537">Iana</comp>
            </collocation>
            <collocation form="pastor cerkve" cluster="11" frequency="75" logDice="5.79">
              <comp position="1" type="headword" sloleks="LE_c4d623bd43bf2e745724193fe576f1c5">pastor</comp>
              <comp position="2" type="collocate" sloleks="LE_71364d2c460f04c8b1dbbb72e4901dca">cerkve</comp>
            </collocation>
          </collocations>
        </gramrel>
      </gramrels>
    </sense>
  </body>
</entry>
