<entry>
  <header>
    <lexical_unit id="79025">podor</lexical_unit>
    <category>samostalnik</category>
    <measure type="frequency" source="Gigafida 1.0">1312</measure>
  </header>
  <body>
    <sense>
      <gramrels>
        <gramrel name="SBZ0 pod sbz6">
          <collocations>
            <collocation form="podor pod Tošec" cluster="1" frequency="11" logDice="13.17">
              <comp position="1" type="headword" sloleks="LE_be79bd7326dd854e2c9177751545db6b">podor</comp>
              <comp position="2" type="other" sloleks="LE_26800b7a10ad4893072d2449bdbbb6f5">pod</comp>
              <comp position="3" type="collocate" sloleks="">Tošec</comp>
            </collocation>
          </collocations>
        </gramrel>
        <gramrel name="SBZ0 v sbz5">
          <collocations>
            <collocation form="podor v kotliču" cluster="1" frequency="8" logDice="11.28">
              <comp position="1" type="headword" sloleks="LE_be79bd7326dd854e2c9177751545db6b">podor</comp>
              <comp position="2" type="other" sloleks="LE_6ee5842d0266489f7232f3339975492f">v</comp>
              <comp position="3" type="collocate" sloleks="LE_5be0dc40f34e81464583ed259a220fae">kotliču</comp>
            </collocation>
            <collocation form="podor v Zatolmin" cluster="2" frequency="4" logDice="10.21">
              <comp position="1" type="headword" sloleks="LE_be79bd7326dd854e2c9177751545db6b">podor</comp>
              <comp position="2" type="other" sloleks="LE_6ee5842d0266489f7232f3339975492f">v</comp>
              <comp position="3" type="collocate" sloleks="">Zatolmin</comp>
            </collocation>
            <collocation form="podor v steni" cluster="3" frequency="12" logDice="6.95">
              <comp position="1" type="headword" sloleks="LE_be79bd7326dd854e2c9177751545db6b">podor</comp>
              <comp position="2" type="other" sloleks="LE_6ee5842d0266489f7232f3339975492f">v</comp>
              <comp position="3" type="collocate" sloleks="LE_47b154875543bbeb3c61452a95a438a3">steni</comp>
            </collocation>
          </collocations>
        </gramrel>
        <gramrel name="gbz do SBZ2">
          <collocations>
            <collocation form="priti do podora" cluster="1" frequency="30" logDice="2.22">
              <comp position="1" type="collocate" sloleks="LE_fc339e29cc0e8ec9efe1ef0acdfb11b5">priti</comp>
              <comp position="2" type="other" sloleks="LE_c7ea3bcd6cdb0ffc6aee490a870fe7b5">do</comp>
              <comp position="3" type="headword" sloleks="LE_be79bd7326dd854e2c9177751545db6b">podora</comp>
            </collocation>
          </collocations>
        </gramrel>
        <gramrel name="gbz z SBZ6">
          <collocations>
            <collocation form="končati s podorom" cluster="1" frequency="4" logDice="1.7">
              <comp position="1" type="collocate" sloleks="LE_bff8ada88a0327f702f1df18714e8d4a">končati</comp>
              <comp position="2" type="other" sloleks="LE_04a0f57716a1e9799e4307c4f13585cf">s</comp>
              <comp position="3" type="headword" sloleks="LE_be79bd7326dd854e2c9177751545db6b">podorom</comp>
            </collocation>
          </collocations>
        </gramrel>
        <gramrel name="gbz za SBZ4">
          <collocations>
            <collocation form="sejati za podor" cluster="1" frequency="10" logDice="10.53">
              <comp position="1" type="collocate" sloleks="LE_82d870ae680ba449cf1471f51b881025">sejati</comp>
              <comp position="2" type="other" sloleks="LE_db0bf52658d522ec13f5839f79903594">za</comp>
              <comp position="3" type="headword" sloleks="LE_be79bd7326dd854e2c9177751545db6b">podor</comp>
            </collocation>
            <collocation form="priporočati za podor" cluster="2" frequency="4" logDice="5.61">
              <comp position="1" type="collocate" sloleks="LE_08a52471b124f5754158c27b6c363a0e">priporočati</comp>
              <comp position="2" type="other" sloleks="LE_db0bf52658d522ec13f5839f79903594">za</comp>
              <comp position="3" type="headword" sloleks="LE_be79bd7326dd854e2c9177751545db6b">podor</comp>
            </collocation>
            <collocation form="uporabiti za podor" cluster="3" frequency="7" logDice="3.59">
              <comp position="1" type="collocate" sloleks="LE_afe0f614dc9e3c90eb71abb7051cdc3a">uporabiti</comp>
              <comp position="2" type="other" sloleks="LE_db0bf52658d522ec13f5839f79903594">za</comp>
              <comp position="3" type="headword" sloleks="LE_be79bd7326dd854e2c9177751545db6b">podor</comp>
            </collocation>
          </collocations>
        </gramrel>
        <gramrel name="pbz0 SBZ0">
          <collocations>
            <collocation form="hribinski podor" cluster="1" frequency="12" logDice="9.15">
              <comp position="1" type="collocate" sloleks="LE_e7385ff2446fa8dff331d3ca54733bb7">hribinski</comp>
              <comp position="2" type="headword" sloleks="LE_be79bd7326dd854e2c9177751545db6b">podor</comp>
            </collocation>
            <collocation form="skalen podor" cluster="2" frequency="149" logDice="9.1">
              <comp position="1" type="collocate" sloleks="LE_1cedd3fbedef71bd4abe1e81239f0d5d">skalen</comp>
              <comp position="2" type="headword" sloleks="LE_be79bd7326dd854e2c9177751545db6b">podor</comp>
            </collocation>
            <collocation form="skalnat podor" cluster="2" frequency="31" logDice="7.86">
              <comp position="1" type="collocate" sloleks="LE_b9ddf78a0ab813b1033c53ee66b57d03">skalnat</comp>
              <comp position="2" type="headword" sloleks="LE_be79bd7326dd854e2c9177751545db6b">podor</comp>
            </collocation>
            <collocation form="kamnit podor" cluster="2" frequency="14" logDice="4.37">
              <comp position="1" type="collocate" sloleks="LE_11245b800453b21e95bfc3d507805968">kamnit</comp>
              <comp position="2" type="headword" sloleks="LE_be79bd7326dd854e2c9177751545db6b">podor</comp>
            </collocation>
            <collocation form="kamninski podor" cluster="3" frequency="8" logDice="7.75">
              <comp position="1" type="collocate" sloleks="LE_86415fa93dbc2ada44664480c657f3ec">kamninski</comp>
              <comp position="2" type="headword" sloleks="LE_be79bd7326dd854e2c9177751545db6b">podor</comp>
            </collocation>
            <collocation form="zelen podor" cluster="4" frequency="141" logDice="5.22">
              <comp position="1" type="collocate" sloleks="LE_6e8aa87791d8f00ce04541edfe194c36">zelen</comp>
              <comp position="2" type="headword" sloleks="LE_be79bd7326dd854e2c9177751545db6b">podor</comp>
            </collocation>
            <collocation form="ogromen podor" cluster="4" frequency="12" logDice="3.09">
              <comp position="1" type="collocate" sloleks="LE_eb4e39c7429c51dcdb97ef1275f59919">ogromen</comp>
              <comp position="2" type="headword" sloleks="LE_be79bd7326dd854e2c9177751545db6b">podor</comp>
            </collocation>
            <collocation form="številen podor" cluster="5" frequency="23" logDice="1.03">
              <comp position="1" type="collocate" sloleks="LE_4f31fb911f8a68938dce145d431affa8">številen</comp>
              <comp position="2" type="headword" sloleks="LE_be79bd7326dd854e2c9177751545db6b">podor</comp>
            </collocation>
          </collocations>
        </gramrel>
        <gramrel name="pbz0 za SBZ4">
          <collocations>
            <collocation form="odličen za podor" cluster="1" frequency="9" logDice="7.37">
              <comp position="1" type="collocate" sloleks="LE_5df9e790d0222ba069d884357b717d12">odličen</comp>
              <comp position="2" type="other" sloleks="LE_db0bf52658d522ec13f5839f79903594">za</comp>
              <comp position="3" type="headword" sloleks="LE_be79bd7326dd854e2c9177751545db6b">podor</comp>
            </collocation>
          </collocations>
        </gramrel>
        <gramrel name="pbz0 zaradi SBZ2">
          <collocations>
            <collocation form="zaprt zaradi podora" cluster="1" frequency="8" logDice="7.83">
              <comp position="1" type="collocate" sloleks="LE_95d102f08d2074a11e0679bd21f77724">zaprt</comp>
              <comp position="2" type="other" sloleks="LE_e2128c24e3c3872c9e5c2981f71b461f">zaradi</comp>
              <comp position="3" type="headword" sloleks="LE_be79bd7326dd854e2c9177751545db6b">podora</comp>
            </collocation>
          </collocations>
        </gramrel>
        <gramrel name="sbz0 SBZ2">
          <collocations>
            <collocation form="sanacija podora" cluster="1" frequency="33" logDice="5.51">
              <comp position="1" type="collocate" sloleks="LE_b37e7e7121cbca14d5bb2913b13f4e3b">sanacija</comp>
              <comp position="2" type="headword" sloleks="LE_be79bd7326dd854e2c9177751545db6b">podora</comp>
            </collocation>
            <collocation form="nevarnost podora" cluster="2" frequency="9" logDice="3.5">
              <comp position="1" type="collocate" sloleks="LE_748e75bfb8d72b22882f959242b3d560">nevarnost</comp>
              <comp position="2" type="headword" sloleks="LE_be79bd7326dd854e2c9177751545db6b">podora</comp>
            </collocation>
            <collocation form="posledica podora" cluster="2" frequency="9" logDice="1.12">
              <comp position="1" type="collocate" sloleks="LE_9e94e198ec2c32de37b2bd7b6e54af2e">posledica</comp>
              <comp position="2" type="headword" sloleks="LE_be79bd7326dd854e2c9177751545db6b">podora</comp>
            </collocation>
            <collocation form="ostanek podora" cluster="3" frequency="7" logDice="2.8">
              <comp position="1" type="collocate" sloleks="LE_1e8f1a48f0110a2a2ede2cf44f8963e5">ostanek</comp>
              <comp position="2" type="headword" sloleks="LE_be79bd7326dd854e2c9177751545db6b">podora</comp>
            </collocation>
            <collocation form="ogled podora" cluster="4" frequency="9" logDice="2.33">
              <comp position="1" type="collocate" sloleks="LE_6d61c73d7a928fcd2e3971cde100ab73">ogled</comp>
              <comp position="2" type="headword" sloleks="LE_be79bd7326dd854e2c9177751545db6b">podora</comp>
            </collocation>
            <collocation form="kraj podora" cluster="5" frequency="7" logDice="1.94">
              <comp position="1" type="collocate" sloleks="LE_7f68ad51dbf6aa81c1b08f8afa92155d">kraj</comp>
              <comp position="2" type="headword" sloleks="LE_be79bd7326dd854e2c9177751545db6b">podora</comp>
            </collocation>
            <collocation form="območje podora" cluster="5" frequency="7" logDice="0.55">
              <comp position="1" type="collocate" sloleks="LE_637bb12e70b217aeada98e77f3559b30">območje</comp>
              <comp position="2" type="headword" sloleks="LE_be79bd7326dd854e2c9177751545db6b">podora</comp>
            </collocation>
            <collocation form="rob podora" cluster="6" frequency="5" logDice="1.41">
              <comp position="1" type="collocate" sloleks="LE_f77fc4e15f47e160c4247e79bf3ae0fc">rob</comp>
              <comp position="2" type="headword" sloleks="LE_be79bd7326dd854e2c9177751545db6b">podora</comp>
            </collocation>
            <collocation form="podor kamenja" cluster="7" frequency="23" logDice="8.59">
              <comp position="1" type="headword" sloleks="LE_be79bd7326dd854e2c9177751545db6b">podor</comp>
              <comp position="2" type="collocate" sloleks="LE_a7964be66d4f9f615ff616da92211d77">kamenja</comp>
            </collocation>
            <collocation form="podor slapa" cluster="8" frequency="16" logDice="8.22">
              <comp position="1" type="headword" sloleks="LE_be79bd7326dd854e2c9177751545db6b">podor</comp>
              <comp position="2" type="collocate" sloleks="LE_02bc5bdc9bd8f87128812ec0592bd53e">slapa</comp>
            </collocation>
            <collocation form="podor skale" cluster="9" frequency="8" logDice="6.63">
              <comp position="1" type="headword" sloleks="LE_be79bd7326dd854e2c9177751545db6b">podor</comp>
              <comp position="2" type="collocate" sloleks="LE_7b56f46b2b5bc0ebd73e0fbaef7c7218">skale</comp>
            </collocation>
          </collocations>
        </gramrel>
        <gramrel name="sbz0 za SBZ4">
          <collocations>
            <collocation form="dosevek za podor" cluster="1" frequency="36" logDice="12.19">
              <comp position="1" type="collocate" sloleks="LE_9455cc9759bfbce588d82e213b766a93">dosevek</comp>
              <comp position="2" type="other" sloleks="LE_db0bf52658d522ec13f5839f79903594">za</comp>
              <comp position="3" type="headword" sloleks="LE_be79bd7326dd854e2c9177751545db6b">podor</comp>
            </collocation>
            <collocation form="posevek za podor" cluster="2" frequency="24" logDice="11.6">
              <comp position="1" type="collocate" sloleks="LE_066558a2014ec675b48920ab9f82b457">posevek</comp>
              <comp position="2" type="other" sloleks="LE_db0bf52658d522ec13f5839f79903594">za</comp>
              <comp position="3" type="headword" sloleks="LE_be79bd7326dd854e2c9177751545db6b">podor</comp>
            </collocation>
            <collocation form="ogrščica za podor" cluster="3" frequency="8" logDice="10.34">
              <comp position="1" type="collocate" sloleks="LE_acdcbe5fe74e00f5a71d1a6edc978aab">ogrščica</comp>
              <comp position="2" type="other" sloleks="LE_db0bf52658d522ec13f5839f79903594">za</comp>
              <comp position="3" type="headword" sloleks="LE_be79bd7326dd854e2c9177751545db6b">podor</comp>
            </collocation>
            <collocation form="rastlina za podor" cluster="4" frequency="80" logDice="10.27">
              <comp position="1" type="collocate" sloleks="LE_29b84db176a06b7dc3d3658f8a3cd001">rastlina</comp>
              <comp position="2" type="other" sloleks="LE_db0bf52658d522ec13f5839f79903594">za</comp>
              <comp position="3" type="headword" sloleks="LE_be79bd7326dd854e2c9177751545db6b">podor</comp>
            </collocation>
          </collocations>
        </gramrel>
      </gramrels>
    </sense>
  </body>
</entry>
