<entry>
  <header>
    <lexical_unit id="96996">vremenar</lexical_unit>
    <category>samostalnik</category>
    <measure type="frequency" source="Gigafida 1.0">1107</measure>
  </header>
  <body>
    <sense>
      <gramrels>
        <gramrel name="pbz0 SBZ0">
          <collocations>
            <collocation form="egoisti훾en vremenar" cluster="1" frequency="13" logDice="8.02">
              <comp position="1" type="collocate" sloleks="LE_3b7e0e046060493161b7fab54f7672b7">egoisti훾en</comp>
              <comp position="2" type="headword" sloleks="LE_d35409d0ca6a1dcac86bb7cc71e53a03">vremenar</comp>
            </collocation>
            <collocation form="nesramen vremenar" cluster="2" frequency="12" logDice="6.78">
              <comp position="1" type="collocate" sloleks="LE_e8c70b132aeff05cafe8d39ec32724b9">nesramen</comp>
              <comp position="2" type="headword" sloleks="LE_d35409d0ca6a1dcac86bb7cc71e53a03">vremenar</comp>
            </collocation>
            <collocation form="znan vremenar" cluster="3" frequency="31" logDice="1.87">
              <comp position="1" type="collocate" sloleks="LE_3ca4e8269ed35ff770799effa47b0eda">znan</comp>
              <comp position="2" type="headword" sloleks="LE_d35409d0ca6a1dcac86bb7cc71e53a03">vremenar</comp>
            </collocation>
            <collocation form="televizijski vremenar" cluster="4" frequency="9" logDice="1.4">
              <comp position="1" type="collocate" sloleks="LE_2e9d37c8647ad3002e4f927d5330c563">televizijski</comp>
              <comp position="2" type="headword" sloleks="LE_d35409d0ca6a1dcac86bb7cc71e53a03">vremenar</comp>
            </collocation>
          </collocations>
        </gramrel>
        <gramrel name="sbz0 SBZ2">
          <collocations>
            <collocation form="napoved vremenarja" cluster="1" frequency="32" logDice="4.79">
              <comp position="1" type="collocate" sloleks="LE_857d50f24958cb465551230f8a46f709">napoved</comp>
              <comp position="2" type="headword" sloleks="LE_d35409d0ca6a1dcac86bb7cc71e53a03">vremenarja</comp>
            </collocation>
            <collocation form="za훾etnica vremenarja" cluster="2" frequency="5" logDice="4.35">
              <comp position="1" type="collocate" sloleks="LE_afd58ac0599ff257aebaeff4dfc77822">za훾etnica</comp>
              <comp position="2" type="headword" sloleks="LE_d35409d0ca6a1dcac86bb7cc71e53a03">vremenarja</comp>
            </collocation>
          </collocations>
        </gramrel>
      </gramrels>
    </sense>
  </body>
</entry>
