<entry>
  <header>
    <lexical_unit id="99938">zodiak</lexical_unit>
    <category>samostalnik</category>
    <measure type="frequency" source="Gigafida 1.0">993</measure>
  </header>
  <body>
    <sense>
      <gramrels>
        <gramrel name="gbz v SBZ5">
          <collocations>
            <collocation form="le탑ati v zodiaku" cluster="1" frequency="4" logDice="3.24">
              <comp position="1" type="collocate" sloleks="LE_6c35ae92ca5f897f949c465c6469f842">le탑ati</comp>
              <comp position="2" type="other" sloleks="LE_6ee5842d0266489f7232f3339975492f">v</comp>
              <comp position="3" type="headword" sloleks="LE_cc419762e44b111f8592de122b08ae28">zodiaku</comp>
            </collocation>
          </collocations>
        </gramrel>
        <gramrel name="pbz0 SBZ0">
          <collocations>
            <collocation form="kitajski zodiak" cluster="1" frequency="47" logDice="4.27">
              <comp position="1" type="collocate" sloleks="LE_fb185a15f7fbc97760ca90b27e8bf70f">kitajski</comp>
              <comp position="2" type="headword" sloleks="LE_cc419762e44b111f8592de122b08ae28">zodiak</comp>
            </collocation>
          </collocations>
        </gramrel>
        <gramrel name="sbz0 SBZ2">
          <collocations>
            <collocation form="ozvezdje zodiaka" cluster="1" frequency="21" logDice="7.93">
              <comp position="1" type="collocate" sloleks="LE_bb3e323a58f15fcea8e0ae753654bd95">ozvezdje</comp>
              <comp position="2" type="headword" sloleks="LE_cc419762e44b111f8592de122b08ae28">zodiaka</comp>
            </collocation>
            <collocation form="탑ival zodiaka" cluster="2" frequency="33" logDice="7.9">
              <comp position="1" type="collocate" sloleks="LE_b6200c4865c660bb286b47ec062ae356">탑ival</comp>
              <comp position="2" type="headword" sloleks="LE_cc419762e44b111f8592de122b08ae28">zodiaka</comp>
            </collocation>
            <collocation form="pas zodiaka" cluster="3" frequency="16" logDice="6.35">
              <comp position="1" type="collocate" sloleks="LE_89ac9c7dc7f715491af648500946332a">pas</comp>
              <comp position="2" type="headword" sloleks="LE_cc419762e44b111f8592de122b08ae28">zodiaka</comp>
            </collocation>
            <collocation form="znamenje zodiaka" cluster="4" frequency="102" logDice="6.27">
              <comp position="1" type="collocate" sloleks="LE_89ced9910fe1652d14eb02bd6bddca8a">znamenje</comp>
              <comp position="2" type="headword" sloleks="LE_cc419762e44b111f8592de122b08ae28">zodiaka</comp>
            </collocation>
            <collocation form="znak zodiaka" cluster="4" frequency="45" logDice="5.1">
              <comp position="1" type="collocate" sloleks="LE_c14b604b2ebc69adbffa17600b4697c8">znak</comp>
              <comp position="2" type="headword" sloleks="LE_cc419762e44b111f8592de122b08ae28">zodiaka</comp>
            </collocation>
            <collocation form="kralj Zodiaka" cluster="5" frequency="8" logDice="3.51">
              <comp position="1" type="collocate" sloleks="LE_d08bfdbe169af8447d4ea3f7e9e60feb">kralj</comp>
              <comp position="2" type="headword" sloleks="LE_cc419762e44b111f8592de122b08ae28">Zodiaka</comp>
            </collocation>
            <collocation form="stopinja zodiaka" cluster="6" frequency="7" logDice="2.9">
              <comp position="1" type="collocate" sloleks="LE_084c0d32be4af09b7c8993adbdbb6baf">stopinja</comp>
              <comp position="2" type="headword" sloleks="LE_cc419762e44b111f8592de122b08ae28">zodiaka</comp>
            </collocation>
            <collocation form="stopnja zodiaka" cluster="7" frequency="5" logDice="0.77">
              <comp position="1" type="collocate" sloleks="LE_ed1cc20afdfdf1e20fe2e301bae175ee">stopnja</comp>
              <comp position="2" type="headword" sloleks="LE_cc419762e44b111f8592de122b08ae28">zodiaka</comp>
            </collocation>
          </collocations>
        </gramrel>
        <gramrel name="sbz0 po SBZ5">
          <collocations>
            <collocation form="flirt po zodiaku" cluster="1" frequency="6" logDice="12.83">
              <comp position="1" type="collocate" sloleks="LE_9d0027a60541a84ec08d4fca17fd9414">flirt</comp>
              <comp position="2" type="other" sloleks="LE_e749ab7a5b937c21d321f46ea8ddde87">po</comp>
              <comp position="3" type="headword" sloleks="LE_cc419762e44b111f8592de122b08ae28">zodiaku</comp>
            </collocation>
          </collocations>
        </gramrel>
        <gramrel name="sbz0 v SBZ5">
          <collocations>
            <collocation form="ozvezdje v zodiaku" cluster="1" frequency="6" logDice="11.35">
              <comp position="1" type="collocate" sloleks="LE_bb3e323a58f15fcea8e0ae753654bd95">ozvezdje</comp>
              <comp position="2" type="other" sloleks="LE_6ee5842d0266489f7232f3339975492f">v</comp>
              <comp position="3" type="headword" sloleks="LE_cc419762e44b111f8592de122b08ae28">zodiaku</comp>
            </collocation>
            <collocation form="znamenje v zodiaku" cluster="2" frequency="11" logDice="9.04">
              <comp position="1" type="collocate" sloleks="LE_89ced9910fe1652d14eb02bd6bddca8a">znamenje</comp>
              <comp position="2" type="other" sloleks="LE_6ee5842d0266489f7232f3339975492f">v</comp>
              <comp position="3" type="headword" sloleks="LE_cc419762e44b111f8592de122b08ae28">zodiaku</comp>
            </collocation>
          </collocations>
        </gramrel>
      </gramrels>
    </sense>
  </body>
</entry>
